mac/__init__.py
mac/api_vendors.py
mac/vendor.py
mac_vendors/__init__.py
mac_vendors/api_vendors.py
mac_vendors/vendor.py
mac_vendors-0.0.5.dist-info/METADATA
mac_vendors-0.0.5.dist-info/WHEEL
mac_vendors-0.0.5.dist-info/top_level.txt
mac_vendors-0.0.5.dist-info/RECORD
