Metadata-Version: 2.1
Name: mac-vendors
Version: 0.0.5
Summary: Get vendor information from a MAC address.
Home-page: https://github.com/brERS/dio.me-bootcamps/tree/main/Gera%C3%A7%C3%A3o%20Tech%20Unimed-BH%20-%20Ci%C3%AAncia%20de%20Dados/Descomplicando%20a%20cria%C3%A7%C3%A3o%20de%20pacotes%20em%20Python
Author: Edgar Reis
License: UNKNOWN
Platform: UNKNOWN
Requires-Python: >=3.8
Requires-Dist: XlsxWriter (>=3.0.3)
Requires-Dist: pandas (>=1.5.0)
Requires-Dist: requests (>=2.25.1)
Requires-Dist: types-requests (>=2.28.11.2)
